gd_icon_composite/__init__.py
gd_icon_composite/icon_composite.py
gd_icon_composite-0.0.8.dist-info/LICENSE
gd_icon_composite-0.0.8.dist-info/METADATA
gd_icon_composite-0.0.8.dist-info/WHEEL
gd_icon_composite-0.0.8.dist-info/top_level.txt
gd_icon_composite-0.0.8.dist-info/RECORD
